huckle/__init__.py
huckle/__main__.py
huckle/config.py
huckle/hclinav.py
huckle/huckle.py
huckle/logger.py
huckle/package.py
huckle/auth/__init__.py
huckle/auth/authenticator.py
huckle/auth/credential.py
huckle/data/huckle.1
huckle-5.7.5.dist-info/LICENSE.txt
huckle-5.7.5.dist-info/METADATA
huckle-5.7.5.dist-info/WHEEL
huckle-5.7.5.dist-info/entry_points.txt
huckle-5.7.5.dist-info/top_level.txt
huckle-5.7.5.dist-info/RECORD
