Metadata-Version: 2.1
Name: huckle
Version: 5.7.5
Summary: A CLI, and python library, that can act as an impostor for any CLI expressed through hypertext command line interface (HCLI) semantics.
Author-email: Jeff Michaud <cometaj2@proton.me>
License: Copyright (c) 2017 Jeff Michaud
Project-URL: Homepage, https://github.com/cometaj2/huckle
Keywords: cli,client,hypermedia,rest,generic,development
Classifier: Development Status :: 4 - Beta
Classifier: Intended Audience :: Developers
Classifier: Topic :: Software Development
Classifier: Programming Language :: Python :: 3.8
Classifier: Programming Language :: Python :: 3.9
Classifier: Programming Language :: Python :: 3.10
Classifier: Programming Language :: Python :: 3.11
Classifier: Programming Language :: Python :: 3.12
License-File: LICENSE.txt
Requires-Dist: restnavigator==1.0.1
Requires-Dist: requests[socks]==2.32.3
Requires-Dist: configparser==5.3.0
Requires-Dist: certifi==2024.12.14
Requires-Dist: portalocker==2.10.1
Requires-Dist: keyring==25.5.0
